mappa/FileHandler.py
mappa/__init__.py
mappa/cli.py
mappa/help.py
mappa_cli-0.0.1.0.dist-info/METADATA
mappa_cli-0.0.1.0.dist-info/WHEEL
mappa_cli-0.0.1.0.dist-info/entry_points.txt
mappa_cli-0.0.1.0.dist-info/top_level.txt
mappa_cli-0.0.1.0.dist-info/RECORD
